{
  "records": [
    {
      "packageReferenceCode": "SLP974157",
      "awbNumber": "103975677",
      "shippedOn": 1459849153000,
      "deliveredOn": null,
      "handoverDate": 1459849153000,
      "courierName": "XpressBees",
      "courierCode": "XPRESSBEES",
      "fulfillmentModeCode": "ONESHIP",
      "fulfillmentMode": "Oneship",
      "invoiceNumber": "",
      "stateFormRequired": false,
      "sdInstant": false,
      "orders": [
        {
          "productImageURL": "http://qan3.sdlcdn.com/imgs/a/a/0/107x125/Mahindra_The_New_Generation_Scorpio_SDL194819370_1_215b4-5d504.jpg",
          "productName": "Non Book Product ",
          "supc": "SDL887500248",
          "sku": "Update Sub category :2014-06-19 10:56:34.277",
          "subOrderId": "44830792",
          "sellingPrice": 8252,
          "paymentMode": "STD",
          "orderDate": 1459503554000,
          "serialNumber": null,
          "siCode": "SI986082",
          "attributes": "",
          "serialNumberType": null,
          "sdInstant": false,
          "paymentDetail": null,
          "status": "Pending for Processing",
          "sellerUnrepliedCount": null,
          "issueReason": null,
          "caseStatus": null,
          "lastContentBody": null,
          "buyerFirstMessageTS": null,
          "buyerName": null,
          "caseId": null,
          "serverTime": null
        }
      ],
      "handoverId": null,
      "manifestedCode": null,
      "fpCode": "OC-DEL",
      "orderSla": null,
      "fastshipSla": null
    },
    {
      "packageReferenceCode": "SLP976393",
      "awbNumber": "103975677",
      "shippedOn": 1459856826000,
      "deliveredOn": null,
      "handoverDate": 1459856826000,
      "courierName": "XpressBees",
      "courierCode": "XPRESSBEES",
      "fulfillmentModeCode": "ONESHIP",
      "fulfillmentMode": "Oneship",
      "invoiceNumber": "",
      "stateFormRequired": false,
      "sdInstant": false,
      "orders": [
        {
          "productImageURL": "http://qan3.sdlcdn.com/imgs/a/a/0/107x125/Mahindra_The_New_Generation_Scorpio_SDL194819370_1_215b4-5d504.jpg",
          "productName": "Non Book Product ",
          "supc": "SDL887500248",
          "sku": "Update Sub category :2014-06-19 10:56:34.277",
          "subOrderId": "44873659",
          "sellingPrice": 1371,
          "paymentMode": "COD",
          "orderDate": 1459511226000,
          "serialNumber": null,
          "siCode": "SI988335",
          "attributes": "",
          "serialNumberType": null,
          "sdInstant": false,
          "paymentDetail": null,
          "status": "Pending for Processing",
          "sellerUnrepliedCount": null,
          "issueReason": null,
          "caseStatus": null,
          "lastContentBody": null,
          "buyerFirstMessageTS": null,
          "buyerName": null,
          "caseId": null,
          "serverTime": null
        }
      ],
      "handoverId": null,
      "manifestedCode": null,
      "fpCode": "OC-DEL",
      "orderSla": null,
      "fastshipSla": null
    },
    {
      "packageReferenceCode": "SLP968558",
      "awbNumber": "103975677",
      "shippedOn": 1459842052000,
      "deliveredOn": null,
      "handoverDate": 1459842052000,
      "courierName": "XpressBees",
      "courierCode": "XPRESSBEES",
      "fulfillmentModeCode": "ONESHIP",
      "fulfillmentMode": "Oneship",
      "invoiceNumber": "",
      "stateFormRequired": false,
      "sdInstant": false,
      "orders": [
        {
          "productImageURL": "http://qan3.sdlcdn.com/imgs/a/a/0/107x125/Mahindra_The_New_Generation_Scorpio_SDL194819370_1_215b4-5d504.jpg",
          "productName": "Non Book Product ",
          "supc": "SDL887500248",
          "sku": "Update Sub category :2014-06-19 10:56:34.277",
          "subOrderId": "44783587",
          "sellingPrice": 8252,
          "paymentMode": "COD",
          "orderDate": 1459496453000,
          "serialNumber": null,
          "siCode": "SI980491",
          "attributes": "",
          "serialNumberType": null,
          "sdInstant": false,
          "paymentDetail": null,
          "status": "Pending for Processing",
          "sellerUnrepliedCount": null,
          "issueReason": null,
          "caseStatus": null,
          "lastContentBody": null,
          "buyerFirstMessageTS": null,
          "buyerName": null,
          "caseId": null,
          "serverTime": null
        }
      ],
      "handoverId": null,
      "manifestedCode": null,
      "fpCode": "OC-DEL",
      "orderSla": null,
      "fastshipSla": null
    },
    {
      "packageReferenceCode": "SLP972055",
      "awbNumber": "103975677",
      "shippedOn": 1459846829000,
      "deliveredOn": null,
      "handoverDate": 1459846829000,
      "courierName": "XpressBees",
      "courierCode": "XPRESSBEES",
      "fulfillmentModeCode": "ONESHIP",
      "fulfillmentMode": "Oneship",
      "invoiceNumber": "",
      "stateFormRequired": false,
      "sdInstant": false,
      "orders": [
        {
          "productImageURL": "http://qan3.sdlcdn.com/imgs/a/a/0/107x125/Mahindra_The_New_Generation_Scorpio_SDL194819370_1_215b4-5d504.jpg",
          "productName": "Non Book Product ",
          "supc": "SDL887500248",
          "sku": "Update Sub category :2014-06-19 10:56:34.277",
          "subOrderId": "44738430",
          "sellingPrice": 8252,
          "paymentMode": "STD",
          "orderDate": 1459501230000,
          "serialNumber": null,
          "siCode": "SI983981",
          "attributes": "",
          "serialNumberType": null,
          "sdInstant": false,
          "paymentDetail": null,
          "status": "Pending for Processing",
          "sellerUnrepliedCount": null,
          "issueReason": null,
          "caseStatus": null,
          "lastContentBody": null,
          "buyerFirstMessageTS": null,
          "buyerName": null,
          "caseId": null,
          "serverTime": null
        }
      ],
      "handoverId": null,
      "manifestedCode": null,
      "fpCode": "OC-DEL",
      "orderSla": null,
      "fastshipSla": null
    },
    {
      "packageReferenceCode": "SLP988466",
      "awbNumber": "103975677",
      "shippedOn": 1459868534000,
      "deliveredOn": null,
      "handoverDate": 1459868534000,
      "courierName": "XpressBees",
      "courierCode": "XPRESSBEES",
      "fulfillmentModeCode": "ONESHIP",
      "fulfillmentMode": "Oneship",
      "invoiceNumber": "",
      "stateFormRequired": false,
      "sdInstant": false,
      "orders": [
        {
          "productImageURL": "http://qan3.sdlcdn.com/imgs/a/a/0/107x125/Mahindra_The_New_Generation_Scorpio_SDL194819370_1_215b4-5d504.jpg",
          "productName": "Non Book Product ",
          "supc": "SDL887500248",
          "sku": "Update Sub category :2014-06-19 10:56:34.277",
          "subOrderId": "44986728",
          "sellingPrice": 1371,
          "paymentMode": "STD",
          "orderDate": 1459522935000,
          "serialNumber": null,
          "siCode": "SI1000446",
          "attributes": "",
          "serialNumberType": null,
          "sdInstant": false,
          "paymentDetail": null,
          "status": "Pending for Processing",
          "sellerUnrepliedCount": null,
          "issueReason": null,
          "caseStatus": null,
          "lastContentBody": null,
          "buyerFirstMessageTS": null,
          "buyerName": null,
          "caseId": null,
          "serverTime": null
        }
      ],
      "handoverId": null,
      "manifestedCode": null,
      "fpCode": "OC-DEL",
      "orderSla": null,
      "fastshipSla": null
    },
    {
      "packageReferenceCode": "SLP982134",
      "awbNumber": "103975677",
      "shippedOn": 1459862670000,
      "deliveredOn": null,
      "handoverDate": 1459862670000,
      "courierName": "XpressBees",
      "courierCode": "XPRESSBEES",
      "fulfillmentModeCode": "ONESHIP",
      "fulfillmentMode": "Oneship",
      "invoiceNumber": "E81B95/16-17/719",
      "stateFormRequired": false,
      "sdInstant": false,
      "orders": [
        {
          "productImageURL": "http://qan3.sdlcdn.com/imgs/a/a/0/107x125/Mahindra_The_New_Generation_Scorpio_SDL194819370_1_215b4-5d504.jpg",
          "productName": "Non Book Product ",
          "supc": "SDL887500248",
          "sku": "Update Sub category :2014-06-19 10:56:34.277",
          "subOrderId": "44940170",
          "sellingPrice": 1371,
          "paymentMode": "STD",
          "orderDate": 1459517071000,
          "serialNumber": null,
          "siCode": "SI994097",
          "attributes": "",
          "serialNumberType": null,
          "sdInstant": false,
          "paymentDetail": null,
          "status": "Pending for Processing",
          "sellerUnrepliedCount": null,
          "issueReason": null,
          "caseStatus": null,
          "lastContentBody": null,
          "buyerFirstMessageTS": null,
          "buyerName": null,
          "caseId": null,
          "serverTime": null
        }
      ],
      "handoverId": null,
      "manifestedCode": null,
      "fpCode": "OC-DEL",
      "orderSla": null,
      "fastshipSla": null
    },
    {
      "packageReferenceCode": "SLP990608",
      "awbNumber": "103975677",
      "shippedOn": 1459873132000,
      "deliveredOn": null,
      "handoverDate": 1459873132000,
      "courierName": "XpressBees",
      "courierCode": "XPRESSBEES",
      "fulfillmentModeCode": "ONESHIP",
      "fulfillmentMode": "Oneship",
      "invoiceNumber": "",
      "stateFormRequired": false,
      "sdInstant": false,
      "orders": [
        {
          "productImageURL": "http://qan3.sdlcdn.com/imgs/a/a/0/107x125/Mahindra_The_New_Generation_Scorpio_SDL194819370_1_215b4-5d504.jpg",
          "productName": "Non Book Product ",
          "supc": "SDL887500248",
          "sku": "Update Sub category :2014-06-19 10:56:34.277",
          "subOrderId": "44948951",
          "sellingPrice": 1371,
          "paymentMode": "STD",
          "orderDate": 1459527841000,
          "serialNumber": null,
          "siCode": "SI1002584",
          "attributes": "",
          "serialNumberType": null,
          "sdInstant": false,
          "paymentDetail": null,
          "status": "Pending for Processing",
          "sellerUnrepliedCount": null,
          "issueReason": null,
          "caseStatus": null,
          "lastContentBody": null,
          "buyerFirstMessageTS": null,
          "buyerName": null,
          "caseId": null,
          "serverTime": null
        }
      ],
      "handoverId": null,
      "manifestedCode": null,
      "fpCode": "OC-DEL",
      "orderSla": null,
      "fastshipSla": null
    },
    {
      "packageReferenceCode": "SLP984927",
      "awbNumber": "103975677",
      "shippedOn": 1459864672000,
      "deliveredOn": null,
      "handoverDate": 1459864672000,
      "courierName": "XpressBees",
      "courierCode": "XPRESSBEES",
      "fulfillmentModeCode": "ONESHIP",
      "fulfillmentMode": "Oneship",
      "invoiceNumber": "",
      "stateFormRequired": false,
      "sdInstant": false,
      "orders": [
        {
          "productImageURL": "http://qan3.sdlcdn.com/imgs/a/a/0/107x125/Mahindra_The_New_Generation_Scorpio_SDL194819370_1_215b4-5d504.jpg",
          "productName": "Non Book Product ",
          "supc": "SDL887500248",
          "sku": "Update Sub category :2014-06-19 10:56:34.277",
          "subOrderId": "44953112",
          "sellingPrice": 1371,
          "paymentMode": "STD",
          "orderDate": 1459519073000,
          "serialNumber": null,
          "siCode": "SI996879",
          "attributes": "",
          "serialNumberType": null,
          "sdInstant": false,
          "paymentDetail": null,
          "status": "Pending for Processing",
          "sellerUnrepliedCount": null,
          "issueReason": null,
          "caseStatus": null,
          "lastContentBody": null,
          "buyerFirstMessageTS": null,
          "buyerName": null,
          "caseId": null,
          "serverTime": null
        }
      ],
      "handoverId": null,
      "manifestedCode": null,
      "fpCode": "OC-DEL",
      "orderSla": null,
      "fastshipSla": null
    },
    {
      "packageReferenceCode": "SLP982889",
      "awbNumber": "103975677",
      "shippedOn": 1459863072000,
      "deliveredOn": null,
      "handoverDate": 1459863072000,
      "courierName": "XpressBees",
      "courierCode": "XPRESSBEES",
      "fulfillmentModeCode": "ONESHIP",
      "fulfillmentMode": "Oneship",
      "invoiceNumber": "E81B95/16-17/744",
      "stateFormRequired": false,
      "sdInstant": false,
      "orders": [
        {
          "productImageURL": "http://qan3.sdlcdn.com/imgs/a/a/0/107x125/Mahindra_The_New_Generation_Scorpio_SDL194819370_1_215b4-5d504.jpg",
          "productName": "Non Book Product ",
          "supc": "SDL887500248",
          "sku": "Update Sub category :2014-06-19 10:56:34.277",
          "subOrderId": "44970955",
          "sellingPrice": 1371,
          "paymentMode": "STD",
          "orderDate": 1459517473000,
          "serialNumber": null,
          "siCode": "SI994842",
          "attributes": "",
          "serialNumberType": null,
          "sdInstant": false,
          "paymentDetail": null,
          "status": "Pending for Processing",
          "sellerUnrepliedCount": null,
          "issueReason": null,
          "caseStatus": null,
          "lastContentBody": null,
          "buyerFirstMessageTS": null,
          "buyerName": null,
          "caseId": null,
          "serverTime": null
        }
      ],
      "handoverId": null,
      "manifestedCode": null,
      "fpCode": "OC-DEL",
      "orderSla": null,
      "fastshipSla": null
    },
    {
      "packageReferenceCode": "SLP986703",
      "awbNumber": "103975677",
      "shippedOn": 1459866408000,
      "deliveredOn": null,
      "handoverDate": 1459866408000,
      "courierName": "XpressBees",
      "courierCode": "XPRESSBEES",
      "fulfillmentModeCode": "ONESHIP",
      "fulfillmentMode": "Oneship",
      "invoiceNumber": "",
      "stateFormRequired": false,
      "sdInstant": false,
      "orders": [
        {
          "productImageURL": "http://qan3.sdlcdn.com/imgs/a/a/0/107x125/Mahindra_The_New_Generation_Scorpio_SDL194819370_1_215b4-5d504.jpg",
          "productName": "Non Book Product ",
          "supc": "SDL887500248",
          "sku": "Update Sub category :2014-06-19 10:56:34.277",
          "subOrderId": "44984828",
          "sellingPrice": 1371,
          "paymentMode": "STD",
          "orderDate": 1459521123000,
          "serialNumber": null,
          "siCode": "SI998689",
          "attributes": "",
          "serialNumberType": null,
          "sdInstant": false,
          "paymentDetail": null,
          "status": "Pending for Processing",
          "sellerUnrepliedCount": null,
          "issueReason": null,
          "caseStatus": null,
          "lastContentBody": null,
          "buyerFirstMessageTS": null,
          "buyerName": null,
          "caseId": null,
          "serverTime": null
        }
      ],
      "handoverId": null,
      "manifestedCode": null,
      "fpCode": "OC-DEL",
      "orderSla": null,
      "fastshipSla": null
    },
    {
      "packageReferenceCode": "SLP982782",
      "awbNumber": "103975677",
      "shippedOn": 1459863007000,
      "deliveredOn": null,
      "handoverDate": 1459863007000,
      "courierName": "XpressBees",
      "courierCode": "XPRESSBEES",
      "fulfillmentModeCode": "ONESHIP",
      "fulfillmentMode": "Oneship",
      "invoiceNumber": "",
      "stateFormRequired": false,
      "sdInstant": false,
      "orders": [
        {
          "productImageURL": "http://qan3.sdlcdn.com/imgs/a/a/0/107x125/Mahindra_The_New_Generation_Scorpio_SDL194819370_1_215b4-5d504.jpg",
          "productName": "Non Book Product ",
          "supc": "SDL887500248",
          "sku": "Update Sub category :2014-06-19 10:56:34.277",
          "subOrderId": "44920848",
          "sellingPrice": 1371,
          "paymentMode": "COD",
          "orderDate": 1459517409000,
          "serialNumber": null,
          "siCode": "SI994745",
          "attributes": "",
          "serialNumberType": null,
          "sdInstant": false,
          "paymentDetail": null,
          "status": "Pending for Processing",
          "sellerUnrepliedCount": null,
          "issueReason": null,
          "caseStatus": null,
          "lastContentBody": null,
          "buyerFirstMessageTS": null,
          "buyerName": null,
          "caseId": null,
          "serverTime": null
        }
      ],
      "handoverId": null,
      "manifestedCode": null,
      "fpCode": "OC-DEL",
      "orderSla": null,
      "fastshipSla": null
    },
    {
      "packageReferenceCode": "SLP971918",
      "awbNumber": "103975677",
      "shippedOn": 1459846617000,
      "deliveredOn": null,
      "handoverDate": 1459846617000,
      "courierName": "XpressBees",
      "courierCode": "XPRESSBEES",
      "fulfillmentModeCode": "ONESHIP",
      "fulfillmentMode": "Oneship",
      "invoiceNumber": "",
      "stateFormRequired": false,
      "sdInstant": false,
      "orders": [
        {
          "productImageURL": "http://qan3.sdlcdn.com/imgs/a/a/0/107x125/Mahindra_The_New_Generation_Scorpio_SDL194819370_1_215b4-5d504.jpg",
          "productName": "Non Book Product ",
          "supc": "SDL887500248",
          "sku": "Update Sub category :2014-06-19 10:56:34.277",
          "subOrderId": "44778295",
          "sellingPrice": 8252,
          "paymentMode": "COD",
          "orderDate": 1459501018000,
          "serialNumber": null,
          "siCode": "SI983842",
          "attributes": "",
          "serialNumberType": null,
          "sdInstant": false,
          "paymentDetail": null,
          "status": "Pending for Processing",
          "sellerUnrepliedCount": null,
          "issueReason": null,
          "caseStatus": null,
          "lastContentBody": null,
          "buyerFirstMessageTS": null,
          "buyerName": null,
          "caseId": null,
          "serverTime": null
        }
      ],
      "handoverId": null,
      "manifestedCode": null,
      "fpCode": "OC-DEL",
      "orderSla": null,
      "fastshipSla": null
    },
    {
      "packageReferenceCode": "SLP970486",
      "awbNumber": "103975677",
      "shippedOn": 1459844987000,
      "deliveredOn": null,
      "handoverDate": 1459844987000,
      "courierName": "XpressBees",
      "courierCode": "XPRESSBEES",
      "fulfillmentModeCode": "ONESHIP",
      "fulfillmentMode": "Oneship",
      "invoiceNumber": "",
      "stateFormRequired": false,
      "sdInstant": false,
      "orders": [
        {
          "productImageURL": "http://qan3.sdlcdn.com/imgs/a/a/0/107x125/Mahindra_The_New_Generation_Scorpio_SDL194819370_1_215b4-5d504.jpg",
          "productName": "Non Book Product ",
          "supc": "SDL887500248",
          "sku": "Update Sub category :2014-06-19 10:56:34.277",
          "subOrderId": "44726655",
          "sellingPrice": 8252,
          "paymentMode": "COD",
          "orderDate": 1459499387000,
          "serialNumber": null,
          "siCode": "SI982418",
          "attributes": "",
          "serialNumberType": null,
          "sdInstant": false,
          "paymentDetail": null,
          "status": "Pending for Processing",
          "sellerUnrepliedCount": null,
          "issueReason": null,
          "caseStatus": null,
          "lastContentBody": null,
          "buyerFirstMessageTS": null,
          "buyerName": null,
          "caseId": null,
          "serverTime": null
        }
      ],
      "handoverId": null,
      "manifestedCode": null,
      "fpCode": "OC-DEL",
      "orderSla": null,
      "fastshipSla": null
    },
    {
      "packageReferenceCode": "SLP970680",
      "awbNumber": "103975677",
      "shippedOn": 1459844795000,
      "deliveredOn": null,
      "handoverDate": 1459844795000,
      "courierName": "XpressBees",
      "courierCode": "XPRESSBEES",
      "fulfillmentModeCode": "ONESHIP",
      "fulfillmentMode": "Oneship",
      "invoiceNumber": "",
      "stateFormRequired": false,
      "sdInstant": false,
      "orders": [
        {
          "productImageURL": "http://qan3.sdlcdn.com/imgs/a/a/0/107x125/Mahindra_The_New_Generation_Scorpio_SDL194819370_1_215b4-5d504.jpg",
          "productName": "Non Book Product ",
          "supc": "SDL887500248",
          "sku": "Update Sub category :2014-06-19 10:56:34.277",
          "subOrderId": "44776448",
          "sellingPrice": 8252,
          "paymentMode": "STD",
          "orderDate": 1459499525000,
          "serialNumber": null,
          "siCode": "SI982618",
          "attributes": "",
          "serialNumberType": null,
          "sdInstant": false,
          "paymentDetail": null,
          "status": "Pending for Processing",
          "sellerUnrepliedCount": null,
          "issueReason": null,
          "caseStatus": null,
          "lastContentBody": null,
          "buyerFirstMessageTS": null,
          "buyerName": null,
          "caseId": null,
          "serverTime": null
        }
      ],
      "handoverId": null,
      "manifestedCode": null,
      "fpCode": "OC-DEL",
      "orderSla": null,
      "fastshipSla": null
    },
    {
      "packageReferenceCode": "SLP981799",
      "awbNumber": "103975677",
      "shippedOn": 1459862457000,
      "deliveredOn": null,
      "handoverDate": 1459862457000,
      "courierName": "XpressBees",
      "courierCode": "XPRESSBEES",
      "fulfillmentModeCode": "ONESHIP",
      "fulfillmentMode": "Oneship",
      "invoiceNumber": "",
      "stateFormRequired": false,
      "sdInstant": false,
      "orders": [
        {
          "productImageURL": "http://qan3.sdlcdn.com/imgs/a/a/0/107x125/Mahindra_The_New_Generation_Scorpio_SDL194819370_1_215b4-5d504.jpg",
          "productName": "Non Book Product ",
          "supc": "SDL887500248",
          "sku": "Update Sub category :2014-06-19 10:56:34.277",
          "subOrderId": "44869791",
          "sellingPrice": 1371,
          "paymentMode": "STD",
          "orderDate": 1459516858000,
          "serialNumber": null,
          "siCode": "SI993758",
          "attributes": "",
          "serialNumberType": null,
          "sdInstant": false,
          "paymentDetail": null,
          "status": "Pending for Processing",
          "sellerUnrepliedCount": null,
          "issueReason": null,
          "caseStatus": null,
          "lastContentBody": null,
          "buyerFirstMessageTS": null,
          "buyerName": null,
          "caseId": null,
          "serverTime": null
        }
      ],
      "handoverId": null,
      "manifestedCode": null,
      "fpCode": "OC-DEL",
      "orderSla": null,
      "fastshipSla": null
    },
    {
      "packageReferenceCode": "SLP982701",
      "awbNumber": "103975677",
      "shippedOn": 1459862962000,
      "deliveredOn": null,
      "handoverDate": 1459862962000,
      "courierName": "XpressBees",
      "courierCode": "XPRESSBEES",
      "fulfillmentModeCode": "ONESHIP",
      "fulfillmentMode": "Oneship",
      "invoiceNumber": "",
      "stateFormRequired": false,
      "sdInstant": false,
      "orders": [
        {
          "productImageURL": "http://qan3.sdlcdn.com/imgs/a/a/0/107x125/Mahindra_The_New_Generation_Scorpio_SDL194819370_1_215b4-5d504.jpg",
          "productName": "Non Book Product ",
          "supc": "SDL887500248",
          "sku": "Update Sub category :2014-06-19 10:56:34.277",
          "subOrderId": "44920773",
          "sellingPrice": 1371,
          "paymentMode": "STD",
          "orderDate": 1459517362000,
          "serialNumber": null,
          "siCode": "SI994667",
          "attributes": "",
          "serialNumberType": null,
          "sdInstant": false,
          "paymentDetail": null,
          "status": "Pending for Processing",
          "sellerUnrepliedCount": null,
          "issueReason": null,
          "caseStatus": null,
          "lastContentBody": null,
          "buyerFirstMessageTS": null,
          "buyerName": null,
          "caseId": null,
          "serverTime": null
        }
      ],
      "handoverId": null,
      "manifestedCode": null,
      "fpCode": "OC-DEL",
      "orderSla": null,
      "fastshipSla": null
    },
    {
      "packageReferenceCode": "SLP988151",
      "awbNumber": "103975677",
      "shippedOn": 1459868273000,
      "deliveredOn": null,
      "handoverDate": 1459868273000,
      "courierName": "XpressBees",
      "courierCode": "XPRESSBEES",
      "fulfillmentModeCode": "ONESHIP",
      "fulfillmentMode": "Oneship",
      "invoiceNumber": "",
      "stateFormRequired": false,
      "sdInstant": false,
      "orders": [
        {
          "productImageURL": "http://qan3.sdlcdn.com/imgs/a/a/0/107x125/Mahindra_The_New_Generation_Scorpio_SDL194819370_1_215b4-5d504.jpg",
          "productName": "Non Book Product ",
          "supc": "SDL887500248",
          "sku": "Update Sub category :2014-06-19 10:56:34.277",
          "subOrderId": "44956473",
          "sellingPrice": 1371,
          "paymentMode": "STD",
          "orderDate": 1459522674000,
          "serialNumber": null,
          "siCode": "SI1000135",
          "attributes": "",
          "serialNumberType": null,
          "sdInstant": false,
          "paymentDetail": null,
          "status": "Pending for Processing",
          "sellerUnrepliedCount": null,
          "issueReason": null,
          "caseStatus": null,
          "lastContentBody": null,
          "buyerFirstMessageTS": null,
          "buyerName": null,
          "caseId": null,
          "serverTime": null
        }
      ],
      "handoverId": null,
      "manifestedCode": null,
      "fpCode": "OC-DEL",
      "orderSla": null,
      "fastshipSla": null
    },
    {
      "packageReferenceCode": "SLP988257",
      "awbNumber": "103975677",
      "shippedOn": 1459868350000,
      "deliveredOn": null,
      "handoverDate": 1459868350000,
      "courierName": "XpressBees",
      "courierCode": "XPRESSBEES",
      "fulfillmentModeCode": "ONESHIP",
      "fulfillmentMode": "Oneship",
      "invoiceNumber": "",
      "stateFormRequired": false,
      "sdInstant": false,
      "orders": [
        {
          "productImageURL": "http://qan3.sdlcdn.com/imgs/a/a/0/107x125/Mahindra_The_New_Generation_Scorpio_SDL194819370_1_215b4-5d504.jpg",
          "productName": "Non Book Product ",
          "supc": "SDL887500248",
          "sku": "Update Sub category :2014-06-19 10:56:34.277",
          "subOrderId": "44936566",
          "sellingPrice": 1371,
          "paymentMode": "COD",
          "orderDate": 1459522750000,
          "serialNumber": null,
          "siCode": "SI1000230",
          "attributes": "",
          "serialNumberType": null,
          "sdInstant": false,
          "paymentDetail": null,
          "status": "Pending for Processing",
          "sellerUnrepliedCount": null,
          "issueReason": null,
          "caseStatus": null,
          "lastContentBody": null,
          "buyerFirstMessageTS": null,
          "buyerName": null,
          "caseId": null,
          "serverTime": null
        }
      ],
      "handoverId": null,
      "manifestedCode": null,
      "fpCode": "OC-DEL",
      "orderSla": null,
      "fastshipSla": null
    },
    {
      "packageReferenceCode": "SLP974050",
      "awbNumber": "103975677",
      "shippedOn": 1459849011000,
      "deliveredOn": null,
      "handoverDate": 1459849011000,
      "courierName": "XpressBees",
      "courierCode": "XPRESSBEES",
      "fulfillmentModeCode": "ONESHIP",
      "fulfillmentMode": "Oneship",
      "invoiceNumber": "",
      "stateFormRequired": false,
      "sdInstant": false,
      "orders": [
        {
          "productImageURL": "http://qan3.sdlcdn.com/imgs/a/a/0/107x125/Mahindra_The_New_Generation_Scorpio_SDL194819370_1_215b4-5d504.jpg",
          "productName": "Non Book Product ",
          "supc": "SDL887500248",
          "sku": "Update Sub category :2014-06-19 10:56:34.277",
          "subOrderId": "44850694",
          "sellingPrice": 8252,
          "paymentMode": "COD",
          "orderDate": 1459503411000,
          "serialNumber": null,
          "siCode": "SI985988",
          "attributes": "",
          "serialNumberType": null,
          "sdInstant": false,
          "paymentDetail": null,
          "status": "Pending for Processing",
          "sellerUnrepliedCount": null,
          "issueReason": null,
          "caseStatus": null,
          "lastContentBody": null,
          "buyerFirstMessageTS": null,
          "buyerName": null,
          "caseId": null,
          "serverTime": null
        }
      ],
      "handoverId": null,
      "manifestedCode": null,
      "fpCode": "OC-DEL",
      "orderSla": null,
      "fastshipSla": null
    },
    {
      "packageReferenceCode": "SLP976234",
      "awbNumber": "103975677",
      "shippedOn": 1459856711000,
      "deliveredOn": null,
      "handoverDate": 1459856711000,
      "courierName": "XpressBees",
      "courierCode": "XPRESSBEES",
      "fulfillmentModeCode": "ONESHIP",
      "fulfillmentMode": "Oneship",
      "invoiceNumber": "",
      "stateFormRequired": false,
      "sdInstant": false,
      "orders": [
        {
          "productImageURL": "http://qan3.sdlcdn.com/imgs/a/a/0/107x125/Mahindra_The_New_Generation_Scorpio_SDL194819370_1_215b4-5d504.jpg",
          "productName": "Non Book Product ",
          "supc": "SDL887500248",
          "sku": "Update Sub category :2014-06-19 10:56:34.277",
          "subOrderId": "44803469",
          "sellingPrice": 1371,
          "paymentMode": "COD",
          "orderDate": 1459511113000,
          "serialNumber": null,
          "siCode": "SI988168",
          "attributes": "",
          "serialNumberType": null,
          "sdInstant": false,
          "paymentDetail": null,
          "status": "Pending for Processing",
          "sellerUnrepliedCount": null,
          "issueReason": null,
          "caseStatus": null,
          "lastContentBody": null,
          "buyerFirstMessageTS": null,
          "buyerName": null,
          "caseId": null,
          "serverTime": null
        }
      ],
      "handoverId": null,
      "manifestedCode": null,
      "fpCode": "OC-DEL",
      "orderSla": null,
      "fastshipSla": null
    },
    {
      "packageReferenceCode": "SLP990641",
      "awbNumber": "103975677",
      "shippedOn": 1459874516000,
      "deliveredOn": null,
      "handoverDate": 1459874516000,
      "courierName": "XpressBees",
      "courierCode": "XPRESSBEES",
      "fulfillmentModeCode": "ONESHIP",
      "fulfillmentMode": "Oneship",
      "invoiceNumber": "",
      "stateFormRequired": false,
      "sdInstant": false,
      "orders": [
        {
          "productImageURL": "http://qan3.sdlcdn.com/imgs/a/a/0/107x125/Mahindra_The_New_Generation_Scorpio_SDL194819370_1_215b4-5d504.jpg",
          "productName": "Non Book Product ",
          "supc": "SDL887500248",
          "sku": "Update Sub category :2014-06-19 10:56:34.277",
          "subOrderId": "44949021",
          "sellingPrice": 1371,
          "paymentMode": "STD",
          "orderDate": 1459529404000,
          "serialNumber": null,
          "siCode": "SI1002628",
          "attributes": "",
          "serialNumberType": null,
          "sdInstant": false,
          "paymentDetail": null,
          "status": "Pending for Processing",
          "sellerUnrepliedCount": null,
          "issueReason": null,
          "caseStatus": null,
          "lastContentBody": null,
          "buyerFirstMessageTS": null,
          "buyerName": null,
          "caseId": null,
          "serverTime": null
        }
      ],
      "handoverId": null,
      "manifestedCode": null,
      "fpCode": "OC-DEL",
      "orderSla": null,
      "fastshipSla": null
    },
    {
      "packageReferenceCode": "SLP970381",
      "awbNumber": "103975677",
      "shippedOn": 1459844861000,
      "deliveredOn": null,
      "handoverDate": 1459844861000,
      "courierName": "XpressBees",
      "courierCode": "XPRESSBEES",
      "fulfillmentModeCode": "ONESHIP",
      "fulfillmentMode": "Oneship",
      "invoiceNumber": "",
      "stateFormRequired": false,
      "sdInstant": false,
      "orders": [
        {
          "productImageURL": "http://qan3.sdlcdn.com/imgs/a/a/0/107x125/Mahindra_The_New_Generation_Scorpio_SDL194819370_1_215b4-5d504.jpg",
          "productName": "Non Book Product ",
          "supc": "SDL887500248",
          "sku": "Update Sub category :2014-06-19 10:56:34.277",
          "subOrderId": "44796537",
          "sellingPrice": 8252,
          "paymentMode": "STD",
          "orderDate": 1459499261000,
          "serialNumber": null,
          "siCode": "SI982314",
          "attributes": "",
          "serialNumberType": null,
          "sdInstant": false,
          "paymentDetail": null,
          "status": "Pending for Processing",
          "sellerUnrepliedCount": null,
          "issueReason": null,
          "caseStatus": null,
          "lastContentBody": null,
          "buyerFirstMessageTS": null,
          "buyerName": null,
          "caseId": null,
          "serverTime": null
        }
      ],
      "handoverId": null,
      "manifestedCode": null,
      "fpCode": "OC-DEL",
      "orderSla": null,
      "fastshipSla": null
    },
    {
      "packageReferenceCode": "SLP972173",
      "awbNumber": "103975677",
      "shippedOn": 1459847007000,
      "deliveredOn": null,
      "handoverDate": 1459847007000,
      "courierName": "XpressBees",
      "courierCode": "XPRESSBEES",
      "fulfillmentModeCode": "ONESHIP",
      "fulfillmentMode": "Oneship",
      "invoiceNumber": "",
      "stateFormRequired": false,
      "sdInstant": false,
      "orders": [
        {
          "productImageURL": "http://qan3.sdlcdn.com/imgs/a/a/0/107x125/Mahindra_The_New_Generation_Scorpio_SDL194819370_1_215b4-5d504.jpg",
          "productName": "Non Book Product ",
          "supc": "SDL887500248",
          "sku": "Update Sub category :2014-06-19 10:56:34.277",
          "subOrderId": "44748571",
          "sellingPrice": 8252,
          "paymentMode": "STD",
          "orderDate": 1459501408000,
          "serialNumber": null,
          "siCode": "SI984104",
          "attributes": "",
          "serialNumberType": null,
          "sdInstant": false,
          "paymentDetail": null,
          "status": "Pending for Processing",
          "sellerUnrepliedCount": null,
          "issueReason": null,
          "caseStatus": null,
          "lastContentBody": null,
          "buyerFirstMessageTS": null,
          "buyerName": null,
          "caseId": null,
          "serverTime": null
        }
      ],
      "handoverId": null,
      "manifestedCode": null,
      "fpCode": "OC-DEL",
      "orderSla": null,
      "fastshipSla": null
    },
    {
      "packageReferenceCode": "SLP975965",
      "awbNumber": "103975677",
      "shippedOn": 1459855208000,
      "deliveredOn": null,
      "handoverDate": 1459855208000,
      "courierName": "XpressBees",
      "courierCode": "XPRESSBEES",
      "fulfillmentModeCode": "ONESHIP",
      "fulfillmentMode": "Oneship",
      "invoiceNumber": "",
      "stateFormRequired": false,
      "sdInstant": false,
      "orders": [
        {
          "productImageURL": "http://qan3.sdlcdn.com/imgs/a/a/0/107x125/Mahindra_The_New_Generation_Scorpio_SDL194819370_1_215b4-5d504.jpg",
          "productName": "Non Book Product ",
          "supc": "SDL887500248",
          "sku": "Update Sub category :2014-06-19 10:56:34.277",
          "subOrderId": "44822961",
          "sellingPrice": 1371,
          "paymentMode": "STD",
          "orderDate": 1459509961000,
          "serialNumber": null,
          "siCode": "SI987898",
          "attributes": "",
          "serialNumberType": null,
          "sdInstant": false,
          "paymentDetail": null,
          "status": "Pending for Processing",
          "sellerUnrepliedCount": null,
          "issueReason": null,
          "caseStatus": null,
          "lastContentBody": null,
          "buyerFirstMessageTS": null,
          "buyerName": null,
          "caseId": null,
          "serverTime": null
        }
      ],
      "handoverId": null,
      "manifestedCode": null,
      "fpCode": "OC-DEL",
      "orderSla": null,
      "fastshipSla": null
    },
    {
      "packageReferenceCode": "SLP976307",
      "awbNumber": "103975677",
      "shippedOn": 1459856754000,
      "deliveredOn": null,
      "handoverDate": 1459856754000,
      "courierName": "XpressBees",
      "courierCode": "XPRESSBEES",
      "fulfillmentModeCode": "ONESHIP",
      "fulfillmentMode": "Oneship",
      "invoiceNumber": "",
      "stateFormRequired": false,
      "sdInstant": false,
      "orders": [
        {
          "productImageURL": "http://qan3.sdlcdn.com/imgs/a/a/0/107x125/Mahindra_The_New_Generation_Scorpio_SDL194819370_1_215b4-5d504.jpg",
          "productName": "Non Book Product ",
          "supc": "SDL887500248",
          "sku": "Update Sub category :2014-06-19 10:56:34.277",
          "subOrderId": "44873538",
          "sellingPrice": 1371,
          "paymentMode": "STD",
          "orderDate": 1459511156000,
          "serialNumber": null,
          "siCode": "SI988231",
          "attributes": "",
          "serialNumberType": null,
          "sdInstant": false,
          "paymentDetail": null,
          "status": "Pending for Processing",
          "sellerUnrepliedCount": null,
          "issueReason": null,
          "caseStatus": null,
          "lastContentBody": null,
          "buyerFirstMessageTS": null,
          "buyerName": null,
          "caseId": null,
          "serverTime": null
        }
      ],
      "handoverId": null,
      "manifestedCode": null,
      "fpCode": "OC-DEL",
      "orderSla": null,
      "fastshipSla": null
    },
    {
      "packageReferenceCode": "SLP986746",
      "awbNumber": "103975677",
      "shippedOn": 1459866452000,
      "deliveredOn": null,
      "handoverDate": 1459866452000,
      "courierName": "XpressBees",
      "courierCode": "XPRESSBEES",
      "fulfillmentModeCode": "ONESHIP",
      "fulfillmentMode": "Oneship",
      "invoiceNumber": "",
      "stateFormRequired": false,
      "sdInstant": false,
      "orders": [
        {
          "productImageURL": "http://qan3.sdlcdn.com/imgs/a/a/0/107x125/Mahindra_The_New_Generation_Scorpio_SDL194819370_1_215b4-5d504.jpg",
          "productName": "Non Book Product ",
          "supc": "SDL887500248",
          "sku": "Update Sub category :2014-06-19 10:56:34.277",
          "subOrderId": "44954842",
          "sellingPrice": 1371,
          "paymentMode": "COD",
          "orderDate": 1459521241000,
          "serialNumber": null,
          "siCode": "SI998728",
          "attributes": "",
          "serialNumberType": null,
          "sdInstant": false,
          "paymentDetail": null,
          "status": "Pending for Processing",
          "sellerUnrepliedCount": null,
          "issueReason": null,
          "caseStatus": null,
          "lastContentBody": null,
          "buyerFirstMessageTS": null,
          "buyerName": null,
          "caseId": null,
          "serverTime": null
        }
      ],
      "handoverId": null,
      "manifestedCode": null,
      "fpCode": "OC-DEL",
      "orderSla": null,
      "fastshipSla": null
    },
    {
      "packageReferenceCode": "SLP989577",
      "awbNumber": "103975677",
      "shippedOn": 1459870042000,
      "deliveredOn": null,
      "handoverDate": 1459870042000,
      "courierName": "XpressBees",
      "courierCode": "XPRESSBEES",
      "fulfillmentModeCode": "ONESHIP",
      "fulfillmentMode": "Oneship",
      "invoiceNumber": "",
      "stateFormRequired": false,
      "sdInstant": false,
      "orders": [
        {
          "productImageURL": "http://qan3.sdlcdn.com/imgs/a/a/0/107x125/Mahindra_The_New_Generation_Scorpio_SDL194819370_1_215b4-5d504.jpg",
          "productName": "Non Book Product ",
          "supc": "SDL887500248",
          "sku": "Update Sub category :2014-06-19 10:56:34.277",
          "subOrderId": "44927957",
          "sellingPrice": 1371,
          "paymentMode": "STD",
          "orderDate": 1459524443000,
          "serialNumber": null,
          "siCode": "SI1001559",
          "attributes": "",
          "serialNumberType": null,
          "sdInstant": false,
          "paymentDetail": null,
          "status": "Pending for Processing",
          "sellerUnrepliedCount": null,
          "issueReason": null,
          "caseStatus": null,
          "lastContentBody": null,
          "buyerFirstMessageTS": null,
          "buyerName": null,
          "caseId": null,
          "serverTime": null
        }
      ],
      "handoverId": null,
      "manifestedCode": null,
      "fpCode": "OC-DEL",
      "orderSla": null,
      "fastshipSla": null
    },
    {
      "packageReferenceCode": "SLP985042",
      "awbNumber": "103975677",
      "shippedOn": 1459864784000,
      "deliveredOn": null,
      "handoverDate": 1459864784000,
      "courierName": "XpressBees",
      "courierCode": "XPRESSBEES",
      "fulfillmentModeCode": "ONESHIP",
      "fulfillmentMode": "Oneship",
      "invoiceNumber": "",
      "stateFormRequired": false,
      "sdInstant": false,
      "orders": [
        {
          "productImageURL": "http://qan3.sdlcdn.com/imgs/a/a/0/107x125/Mahindra_The_New_Generation_Scorpio_SDL194819370_1_215b4-5d504.jpg",
          "productName": "Non Book Product ",
          "supc": "SDL887500248",
          "sku": "Update Sub category :2014-06-19 10:56:34.277",
          "subOrderId": "44913214",
          "sellingPrice": 1371,
          "paymentMode": "STD",
          "orderDate": 1459519186000,
          "serialNumber": null,
          "siCode": "SI996995",
          "attributes": "",
          "serialNumberType": null,
          "sdInstant": false,
          "paymentDetail": null,
          "status": "Pending for Processing",
          "sellerUnrepliedCount": null,
          "issueReason": null,
          "caseStatus": null,
          "lastContentBody": null,
          "buyerFirstMessageTS": null,
          "buyerName": null,
          "caseId": null,
          "serverTime": null
        }
      ],
      "handoverId": null,
      "manifestedCode": null,
      "fpCode": "OC-DEL",
      "orderSla": null,
      "fastshipSla": null
    },
    {
      "packageReferenceCode": "SLP968607",
      "awbNumber": "103975677",
      "shippedOn": 1459842154000,
      "deliveredOn": null,
      "handoverDate": 1459842154000,
      "courierName": "XpressBees",
      "courierCode": "XPRESSBEES",
      "fulfillmentModeCode": "ONESHIP",
      "fulfillmentMode": "Oneship",
      "invoiceNumber": "",
      "stateFormRequired": false,
      "sdInstant": false,
      "orders": [
        {
          "productImageURL": "http://qan3.sdlcdn.com/imgs/a/a/0/107x125/Mahindra_The_New_Generation_Scorpio_SDL194819370_1_215b4-5d504.jpg",
          "productName": "Non Book Product ",
          "supc": "SDL887500248",
          "sku": "Update Sub category :2014-06-19 10:56:34.277",
          "subOrderId": "44723641",
          "sellingPrice": 8252,
          "paymentMode": "STD",
          "orderDate": 1459496554000,
          "serialNumber": null,
          "siCode": "SI980540",
          "attributes": "",
          "serialNumberType": null,
          "sdInstant": false,
          "paymentDetail": null,
          "status": "Pending for Processing",
          "sellerUnrepliedCount": null,
          "issueReason": null,
          "caseStatus": null,
          "lastContentBody": null,
          "buyerFirstMessageTS": null,
          "buyerName": null,
          "caseId": null,
          "serverTime": null
        }
      ],
      "handoverId": null,
      "manifestedCode": null,
      "fpCode": "OC-DEL",
      "orderSla": null,
      "fastshipSla": null
    },
    {
      "packageReferenceCode": "SLP982684",
      "awbNumber": "103975677",
      "shippedOn": 1459862955000,
      "deliveredOn": null,
      "handoverDate": 1459862955000,
      "courierName": "XpressBees",
      "courierCode": "XPRESSBEES",
      "fulfillmentModeCode": "ONESHIP",
      "fulfillmentMode": "Oneship",
      "invoiceNumber": "",
      "stateFormRequired": false,
      "sdInstant": false,
      "orders": [
        {
          "productImageURL": "http://qan3.sdlcdn.com/imgs/a/a/0/107x125/Mahindra_The_New_Generation_Scorpio_SDL194819370_1_215b4-5d504.jpg",
          "productName": "Non Book Product ",
          "supc": "SDL887500248",
          "sku": "Update Sub category :2014-06-19 10:56:34.277",
          "subOrderId": "44920754",
          "sellingPrice": 1371,
          "paymentMode": "STD",
          "orderDate": 1459517356000,
          "serialNumber": null,
          "siCode": "SI994644",
          "attributes": "",
          "serialNumberType": null,
          "sdInstant": false,
          "paymentDetail": null,
          "status": "Pending for Processing",
          "sellerUnrepliedCount": null,
          "issueReason": null,
          "caseStatus": null,
          "lastContentBody": null,
          "buyerFirstMessageTS": null,
          "buyerName": null,
          "caseId": null,
          "serverTime": null
        }
      ],
      "handoverId": null,
      "manifestedCode": null,
      "fpCode": "OC-DEL",
      "orderSla": null,
      "fastshipSla": null
    },
    {
      "packageReferenceCode": "SLP986786",
      "awbNumber": "103975677",
      "shippedOn": 1459866916000,
      "deliveredOn": null,
      "handoverDate": 1459866916000,
      "courierName": "XpressBees",
      "courierCode": "XPRESSBEES",
      "fulfillmentModeCode": "ONESHIP",
      "fulfillmentMode": "Oneship",
      "invoiceNumber": "",
      "stateFormRequired": false,
      "sdInstant": false,
      "orders": [
        {
          "productImageURL": "http://qan3.sdlcdn.com/imgs/a/a/0/107x125/Mahindra_The_New_Generation_Scorpio_SDL194819370_1_215b4-5d504.jpg",
          "productName": "Non Book Product ",
          "supc": "SDL887500248",
          "sku": "Update Sub category :2014-06-19 10:56:34.277",
          "subOrderId": "44945084",
          "sellingPrice": 1371,
          "paymentMode": "STD",
          "orderDate": 1459521318000,
          "serialNumber": null,
          "siCode": "SI998766",
          "attributes": "",
          "serialNumberType": null,
          "sdInstant": false,
          "paymentDetail": null,
          "status": "Pending for Processing",
          "sellerUnrepliedCount": null,
          "issueReason": null,
          "caseStatus": null,
          "lastContentBody": null,
          "buyerFirstMessageTS": null,
          "buyerName": null,
          "caseId": null,
          "serverTime": null
        }
      ],
      "handoverId": null,
      "manifestedCode": null,
      "fpCode": "OC-DEL",
      "orderSla": null,
      "fastshipSla": null
    },
    {
      "packageReferenceCode": "SLP985187",
      "awbNumber": "103975677",
      "shippedOn": 1459864885000,
      "deliveredOn": null,
      "handoverDate": 1459864885000,
      "courierName": "XpressBees",
      "courierCode": "XPRESSBEES",
      "fulfillmentModeCode": "ONESHIP",
      "fulfillmentMode": "Oneship",
      "invoiceNumber": "",
      "stateFormRequired": false,
      "sdInstant": false,
      "orders": [
        {
          "productImageURL": "http://qan3.sdlcdn.com/imgs/a/a/0/107x125/Mahindra_The_New_Generation_Scorpio_SDL194819370_1_215b4-5d504.jpg",
          "productName": "Non Book Product ",
          "supc": "SDL887500248",
          "sku": "Update Sub category :2014-06-19 10:56:34.277",
          "subOrderId": "44923358",
          "sellingPrice": 1371,
          "paymentMode": "COD",
          "orderDate": 1459519286000,
          "serialNumber": null,
          "siCode": "SI997135",
          "attributes": "",
          "serialNumberType": null,
          "sdInstant": false,
          "paymentDetail": null,
          "status": "Pending for Processing",
          "sellerUnrepliedCount": null,
          "issueReason": null,
          "caseStatus": null,
          "lastContentBody": null,
          "buyerFirstMessageTS": null,
          "buyerName": null,
          "caseId": null,
          "serverTime": null
        }
      ],
      "handoverId": null,
      "manifestedCode": null,
      "fpCode": "OC-DEL",
      "orderSla": null,
      "fastshipSla": null
    },
    {
      "packageReferenceCode": "SLP982051",
      "awbNumber": "103975677",
      "shippedOn": 1459862637000,
      "deliveredOn": null,
      "handoverDate": 1459862637000,
      "courierName": "XpressBees",
      "courierCode": "XPRESSBEES",
      "fulfillmentModeCode": "ONESHIP",
      "fulfillmentMode": "Oneship",
      "invoiceNumber": "E81B95/16-17/716",
      "stateFormRequired": false,
      "sdInstant": false,
      "orders": [
        {
          "productImageURL": "http://qan3.sdlcdn.com/imgs/a/a/0/107x125/Mahindra_The_New_Generation_Scorpio_SDL194819370_1_215b4-5d504.jpg",
          "productName": "Non Book Product ",
          "supc": "SDL887500248",
          "sku": "Update Sub category :2014-06-19 10:56:34.277",
          "subOrderId": "44930092",
          "sellingPrice": 1371,
          "paymentMode": "COD",
          "orderDate": 1459517037000,
          "serialNumber": null,
          "siCode": "SI994014",
          "attributes": "",
          "serialNumberType": null,
          "sdInstant": false,
          "paymentDetail": null,
          "status": "Pending for Processing",
          "sellerUnrepliedCount": null,
          "issueReason": null,
          "caseStatus": null,
          "lastContentBody": null,
          "buyerFirstMessageTS": null,
          "buyerName": null,
          "caseId": null,
          "serverTime": null
        }
      ],
      "handoverId": null,
      "manifestedCode": null,
      "fpCode": "OC-DEL",
      "orderSla": null,
      "fastshipSla": null
    },
    {
      "packageReferenceCode": "SLP985057",
      "awbNumber": "103975677",
      "shippedOn": 1459864789000,
      "deliveredOn": null,
      "handoverDate": 1459864789000,
      "courierName": "XpressBees",
      "courierCode": "XPRESSBEES",
      "fulfillmentModeCode": "ONESHIP",
      "fulfillmentMode": "Oneship",
      "invoiceNumber": "E81B95/16-17/834",
      "stateFormRequired": false,
      "sdInstant": false,
      "orders": [
        {
          "productImageURL": "http://qan3.sdlcdn.com/imgs/a/a/0/107x125/Mahindra_The_New_Generation_Scorpio_SDL194819370_1_215b4-5d504.jpg",
          "productName": "Non Book Product ",
          "supc": "SDL887500248",
          "sku": "Update Sub category :2014-06-19 10:56:34.277",
          "subOrderId": "44973234",
          "sellingPrice": 1371,
          "paymentMode": "STD",
          "orderDate": 1459519189000,
          "serialNumber": null,
          "siCode": "SI997009",
          "attributes": "",
          "serialNumberType": null,
          "sdInstant": false,
          "paymentDetail": null,
          "status": "Pending for Processing",
          "sellerUnrepliedCount": null,
          "issueReason": null,
          "caseStatus": null,
          "lastContentBody": null,
          "buyerFirstMessageTS": null,
          "buyerName": null,
          "caseId": null,
          "serverTime": null
        }
      ],
      "handoverId": null,
      "manifestedCode": null,
      "fpCode": "OC-DEL",
      "orderSla": null,
      "fastshipSla": null
    },
    {
      "packageReferenceCode": "SLP989531",
      "awbNumber": "103975677",
      "shippedOn": 1459869965000,
      "deliveredOn": null,
      "handoverDate": 1459869965000,
      "courierName": "XpressBees",
      "courierCode": "XPRESSBEES",
      "fulfillmentModeCode": "ONESHIP",
      "fulfillmentMode": "Oneship",
      "invoiceNumber": "",
      "stateFormRequired": false,
      "sdInstant": false,
      "orders": [
        {
          "productImageURL": "http://qan3.sdlcdn.com/imgs/a/a/0/107x125/Mahindra_The_New_Generation_Scorpio_SDL194819370_1_215b4-5d504.jpg",
          "productName": "Non Book Product ",
          "supc": "SDL887500248",
          "sku": "Update Sub category :2014-06-19 10:56:34.277",
          "subOrderId": "44907894",
          "sellingPrice": 1371,
          "paymentMode": "STD",
          "orderDate": 1459524365000,
          "serialNumber": null,
          "siCode": "SI1001515",
          "attributes": "",
          "serialNumberType": null,
          "sdInstant": false,
          "paymentDetail": null,
          "status": "Pending for Processing",
          "sellerUnrepliedCount": null,
          "issueReason": null,
          "caseStatus": null,
          "lastContentBody": null,
          "buyerFirstMessageTS": null,
          "buyerName": null,
          "caseId": null,
          "serverTime": null
        }
      ],
      "handoverId": null,
      "manifestedCode": null,
      "fpCode": "OC-DEL",
      "orderSla": null,
      "fastshipSla": null
    },
    {
      "packageReferenceCode": "SLP990625",
      "awbNumber": "103975677",
      "shippedOn": 1459873532000,
      "deliveredOn": null,
      "handoverDate": 1459873532000,
      "courierName": "XpressBees",
      "courierCode": "XPRESSBEES",
      "fulfillmentModeCode": "ONESHIP",
      "fulfillmentMode": "Oneship",
      "invoiceNumber": "",
      "stateFormRequired": false,
      "sdInstant": false,
      "orders": [
        {
          "productImageURL": "http://qan3.sdlcdn.com/imgs/a/a/0/107x125/Mahindra_The_New_Generation_Scorpio_SDL194819370_1_215b4-5d504.jpg",
          "productName": "Non Book Product ",
          "supc": "SDL887500248",
          "sku": "Update Sub category :2014-06-19 10:56:34.277",
          "subOrderId": "44938985",
          "sellingPrice": 1371,
          "paymentMode": "STD",
          "orderDate": 1459528321000,
          "serialNumber": null,
          "siCode": "SI1002609",
          "attributes": "",
          "serialNumberType": null,
          "sdInstant": false,
          "paymentDetail": null,
          "status": "Pending for Processing",
          "sellerUnrepliedCount": null,
          "issueReason": null,
          "caseStatus": null,
          "lastContentBody": null,
          "buyerFirstMessageTS": null,
          "buyerName": null,
          "caseId": null,
          "serverTime": null
        }
      ],
      "handoverId": null,
      "manifestedCode": null,
      "fpCode": "OC-DEL",
      "orderSla": null,
      "fastshipSla": null
    },
    {
      "packageReferenceCode": "SLP982154",
      "awbNumber": "103975677",
      "shippedOn": 1459862683000,
      "deliveredOn": null,
      "handoverDate": 1459862683000,
      "courierName": "XpressBees",
      "courierCode": "XPRESSBEES",
      "fulfillmentModeCode": "ONESHIP",
      "fulfillmentMode": "Oneship",
      "invoiceNumber": "",
      "stateFormRequired": false,
      "sdInstant": false,
      "orders": [
        {
          "productImageURL": "http://qan3.sdlcdn.com/imgs/a/a/0/107x125/Mahindra_The_New_Generation_Scorpio_SDL194819370_1_215b4-5d504.jpg",
          "productName": "Non Book Product ",
          "supc": "SDL887500248",
          "sku": "Update Sub category :2014-06-19 10:56:34.277",
          "subOrderId": "44930196",
          "sellingPrice": 1371,
          "paymentMode": "COD",
          "orderDate": 1459517084000,
          "serialNumber": null,
          "siCode": "SI994114",
          "attributes": "",
          "serialNumberType": null,
          "sdInstant": false,
          "paymentDetail": null,
          "status": "Pending for Processing",
          "sellerUnrepliedCount": null,
          "issueReason": null,
          "caseStatus": null,
          "lastContentBody": null,
          "buyerFirstMessageTS": null,
          "buyerName": null,
          "caseId": null,
          "serverTime": null
        }
      ],
      "handoverId": null,
      "manifestedCode": null,
      "fpCode": "OC-DEL",
      "orderSla": null,
      "fastshipSla": null
    },
    {
      "packageReferenceCode": "SLP970428",
      "awbNumber": "103975677",
      "shippedOn": 1459844561000,
      "deliveredOn": null,
      "handoverDate": 1459844561000,
      "courierName": "XpressBees",
      "courierCode": "XPRESSBEES",
      "fulfillmentModeCode": "ONESHIP",
      "fulfillmentMode": "Oneship",
      "invoiceNumber": "",
      "stateFormRequired": false,
      "sdInstant": false,
      "orders": [
        {
          "productImageURL": "http://qan3.sdlcdn.com/imgs/a/a/0/107x125/Mahindra_The_New_Generation_Scorpio_SDL194819370_1_215b4-5d504.jpg",
          "productName": "Non Book Product ",
          "supc": "SDL887500248",
          "sku": "Update Sub category :2014-06-19 10:56:34.277",
          "subOrderId": "44706116",
          "sellingPrice": 8252,
          "paymentMode": "STD",
          "orderDate": 1459499283000,
          "serialNumber": null,
          "siCode": "SI982357",
          "attributes": "",
          "serialNumberType": null,
          "sdInstant": false,
          "paymentDetail": null,
          "status": "Pending for Processing",
          "sellerUnrepliedCount": null,
          "issueReason": null,
          "caseStatus": null,
          "lastContentBody": null,
          "buyerFirstMessageTS": null,
          "buyerName": null,
          "caseId": null,
          "serverTime": null
        }
      ],
      "handoverId": null,
      "manifestedCode": null,
      "fpCode": "OC-DEL",
      "orderSla": null,
      "fastshipSla": null
    },
    {
      "packageReferenceCode": "SLP989634",
      "awbNumber": "103975677",
      "shippedOn": 1459870118000,
      "deliveredOn": null,
      "handoverDate": 1459870118000,
      "courierName": "XpressBees",
      "courierCode": "XPRESSBEES",
      "fulfillmentModeCode": "ONESHIP",
      "fulfillmentMode": "Oneship",
      "invoiceNumber": "",
      "stateFormRequired": false,
      "sdInstant": false,
      "orders": [
        {
          "productImageURL": "http://qan3.sdlcdn.com/imgs/a/a/0/107x125/Mahindra_The_New_Generation_Scorpio_SDL194819370_1_215b4-5d504.jpg",
          "productName": "Non Book Product ",
          "supc": "SDL887500248",
          "sku": "Update Sub category :2014-06-19 10:56:34.277",
          "subOrderId": "44928012",
          "sellingPrice": 1371,
          "paymentMode": "COD",
          "orderDate": 1459524519000,
          "serialNumber": null,
          "siCode": "SI1001614",
          "attributes": "",
          "serialNumberType": null,
          "sdInstant": false,
          "paymentDetail": null,
          "status": "Pending for Processing",
          "sellerUnrepliedCount": null,
          "issueReason": null,
          "caseStatus": null,
          "lastContentBody": null,
          "buyerFirstMessageTS": null,
          "buyerName": null,
          "caseId": null,
          "serverTime": null
        }
      ],
      "handoverId": null,
      "manifestedCode": null,
      "fpCode": "OC-DEL",
      "orderSla": null,
      "fastshipSla": null
    },
    {
      "packageReferenceCode": "SLP968441",
      "awbNumber": "103975677",
      "shippedOn": 1459841836000,
      "deliveredOn": null,
      "handoverDate": 1459841836000,
      "courierName": "XpressBees",
      "courierCode": "XPRESSBEES",
      "fulfillmentModeCode": "ONESHIP",
      "fulfillmentMode": "Oneship",
      "invoiceNumber": "",
      "stateFormRequired": false,
      "sdInstant": false,
      "orders": [
        {
          "productImageURL": "http://qan3.sdlcdn.com/imgs/a/a/0/107x125/Mahindra_The_New_Generation_Scorpio_SDL194819370_1_215b4-5d504.jpg",
          "productName": "Non Book Product ",
          "supc": "SDL887500248",
          "sku": "Update Sub category :2014-06-19 10:56:34.277",
          "subOrderId": "44773427",
          "sellingPrice": 8252,
          "paymentMode": "COD",
          "orderDate": 1459496236000,
          "serialNumber": null,
          "siCode": "SI980387",
          "attributes": "",
          "serialNumberType": null,
          "sdInstant": false,
          "paymentDetail": null,
          "status": "Pending for Processing",
          "sellerUnrepliedCount": null,
          "issueReason": null,
          "caseStatus": null,
          "lastContentBody": null,
          "buyerFirstMessageTS": null,
          "buyerName": null,
          "caseId": null,
          "serverTime": null
        }
      ],
      "handoverId": null,
      "manifestedCode": null,
      "fpCode": "OC-DEL",
      "orderSla": null,
      "fastshipSla": null
    },
    {
      "packageReferenceCode": "SLP974212",
      "awbNumber": "103975677",
      "shippedOn": 1459849216000,
      "deliveredOn": null,
      "handoverDate": 1459849216000,
      "courierName": "XpressBees",
      "courierCode": "XPRESSBEES",
      "fulfillmentModeCode": "ONESHIP",
      "fulfillmentMode": "Oneship",
      "invoiceNumber": "",
      "stateFormRequired": false,
      "sdInstant": false,
      "orders": [
        {
          "productImageURL": "http://qan3.sdlcdn.com/imgs/a/a/0/107x125/Mahindra_The_New_Generation_Scorpio_SDL194819370_1_215b4-5d504.jpg",
          "productName": "Non Book Product ",
          "supc": "SDL887500248",
          "sku": "Update Sub category :2014-06-19 10:56:34.277",
          "subOrderId": "44800861",
          "sellingPrice": 8252,
          "paymentMode": "COD",
          "orderDate": 1459503617000,
          "serialNumber": null,
          "siCode": "SI986141",
          "attributes": "",
          "serialNumberType": null,
          "sdInstant": false,
          "paymentDetail": null,
          "status": "Pending for Processing",
          "sellerUnrepliedCount": null,
          "issueReason": null,
          "caseStatus": null,
          "lastContentBody": null,
          "buyerFirstMessageTS": null,
          "buyerName": null,
          "caseId": null,
          "serverTime": null
        }
      ],
      "handoverId": null,
      "manifestedCode": null,
      "fpCode": "OC-DEL",
      "orderSla": null,
      "fastshipSla": null
    },
    {
      "packageReferenceCode": "SLP985295",
      "awbNumber": "103975677",
      "shippedOn": 1459864980000,
      "deliveredOn": null,
      "handoverDate": 1459864980000,
      "courierName": "XpressBees",
      "courierCode": "XPRESSBEES",
      "fulfillmentModeCode": "ONESHIP",
      "fulfillmentMode": "Oneship",
      "invoiceNumber": "",
      "stateFormRequired": false,
      "sdInstant": false,
      "orders": [
        {
          "productImageURL": "http://qan3.sdlcdn.com/imgs/a/a/0/107x125/Mahindra_The_New_Generation_Scorpio_SDL194819370_1_215b4-5d504.jpg",
          "productName": "Non Book Product ",
          "supc": "SDL887500248",
          "sku": "Update Sub category :2014-06-19 10:56:34.277",
          "subOrderId": "44953461",
          "sellingPrice": 1371,
          "paymentMode": "STD",
          "orderDate": 1459519382000,
          "serialNumber": null,
          "siCode": "SI997243",
          "attributes": "",
          "serialNumberType": null,
          "sdInstant": false,
          "paymentDetail": null,
          "status": "Pending for Processing",
          "sellerUnrepliedCount": null,
          "issueReason": null,
          "caseStatus": null,
          "lastContentBody": null,
          "buyerFirstMessageTS": null,
          "buyerName": null,
          "caseId": null,
          "serverTime": null
        }
      ],
      "handoverId": null,
      "manifestedCode": null,
      "fpCode": "OC-DEL",
      "orderSla": null,
      "fastshipSla": null
    },
    {
      "packageReferenceCode": "SLP989464",
      "awbNumber": "103975677",
      "shippedOn": 1459869887000,
      "deliveredOn": null,
      "handoverDate": 1459869887000,
      "courierName": "XpressBees",
      "courierCode": "XPRESSBEES",
      "fulfillmentModeCode": "ONESHIP",
      "fulfillmentMode": "Oneship",
      "invoiceNumber": "",
      "stateFormRequired": false,
      "sdInstant": false,
      "orders": [
        {
          "productImageURL": "http://qan3.sdlcdn.com/imgs/a/a/0/107x125/Mahindra_The_New_Generation_Scorpio_SDL194819370_1_215b4-5d504.jpg",
          "productName": "Non Book Product ",
          "supc": "SDL887500248",
          "sku": "Update Sub category :2014-06-19 10:56:34.277",
          "subOrderId": "44937831",
          "sellingPrice": 1371,
          "paymentMode": "COD",
          "orderDate": 1459524287000,
          "serialNumber": null,
          "siCode": "SI1001442",
          "attributes": "",
          "serialNumberType": null,
          "sdInstant": false,
          "paymentDetail": null,
          "status": "Pending for Processing",
          "sellerUnrepliedCount": null,
          "issueReason": null,
          "caseStatus": null,
          "lastContentBody": null,
          "buyerFirstMessageTS": null,
          "buyerName": null,
          "caseId": null,
          "serverTime": null
        }
      ],
      "handoverId": null,
      "manifestedCode": null,
      "fpCode": "OC-DEL",
      "orderSla": null,
      "fastshipSla": null
    },
    {
      "packageReferenceCode": "SLP986631",
      "awbNumber": "103975677",
      "shippedOn": 1459858750000,
      "deliveredOn": null,
      "handoverDate": 1459858750000,
      "courierName": "XpressBees",
      "courierCode": "XPRESSBEES",
      "fulfillmentModeCode": "ONESHIP",
      "fulfillmentMode": "Oneship",
      "invoiceNumber": "",
      "stateFormRequired": false,
      "sdInstant": false,
      "orders": [
        {
          "productImageURL": "http://qan3.sdlcdn.com/imgs/a/a/0/107x125/Mahindra_The_New_Generation_Scorpio_SDL194819370_1_215b4-5d504.jpg",
          "productName": "Non Book Product ",
          "supc": "SDL887500248",
          "sku": "Update Sub category :2014-06-19 10:56:34.277",
          "subOrderId": "44845409",
          "sellingPrice": 1371,
          "paymentMode": "STD",
          "orderDate": 1459521033000,
          "serialNumber": null,
          "siCode": "SI998614",
          "attributes": "",
          "serialNumberType": null,
          "sdInstant": false,
          "paymentDetail": null,
          "status": "Pending for Processing",
          "sellerUnrepliedCount": null,
          "issueReason": null,
          "caseStatus": null,
          "lastContentBody": null,
          "buyerFirstMessageTS": null,
          "buyerName": null,
          "caseId": null,
          "serverTime": null
        }
      ],
      "handoverId": null,
      "manifestedCode": null,
      "fpCode": "OC-DEL",
      "orderSla": null,
      "fastshipSla": null
    },
    {
      "packageReferenceCode": "SLP981963",
      "awbNumber": "103975677",
      "shippedOn": 1459862569000,
      "deliveredOn": null,
      "handoverDate": 1459862569000,
      "courierName": "XpressBees",
      "courierCode": "XPRESSBEES",
      "fulfillmentModeCode": "ONESHIP",
      "fulfillmentMode": "Oneship",
      "invoiceNumber": "",
      "stateFormRequired": false,
      "sdInstant": false,
      "orders": [
        {
          "productImageURL": "http://qan3.sdlcdn.com/imgs/a/a/0/107x125/Mahindra_The_New_Generation_Scorpio_SDL194819370_1_215b4-5d504.jpg",
          "productName": "Non Book Product ",
          "supc": "SDL887500248",
          "sku": "Update Sub category :2014-06-19 10:56:34.277",
          "subOrderId": "44899953",
          "sellingPrice": 1371,
          "paymentMode": "STD",
          "orderDate": 1459516970000,
          "serialNumber": null,
          "siCode": "SI993923",
          "attributes": "",
          "serialNumberType": null,
          "sdInstant": false,
          "paymentDetail": null,
          "status": "Pending for Processing",
          "sellerUnrepliedCount": null,
          "issueReason": null,
          "caseStatus": null,
          "lastContentBody": null,
          "buyerFirstMessageTS": null,
          "buyerName": null,
          "caseId": null,
          "serverTime": null
        }
      ],
      "handoverId": null,
      "manifestedCode": null,
      "fpCode": "OC-DEL",
      "orderSla": null,
      "fastshipSla": null
    },
    {
      "packageReferenceCode": "SLP972206",
      "awbNumber": "103975677",
      "shippedOn": 1459846707000,
      "deliveredOn": null,
      "handoverDate": 1459846707000,
      "courierName": "XpressBees",
      "courierCode": "XPRESSBEES",
      "fulfillmentModeCode": "ONESHIP",
      "fulfillmentMode": "Oneship",
      "invoiceNumber": "",
      "stateFormRequired": false,
      "sdInstant": false,
      "orders": [
        {
          "productImageURL": "http://qan3.sdlcdn.com/imgs/a/a/0/107x125/Mahindra_The_New_Generation_Scorpio_SDL194819370_1_215b4-5d504.jpg",
          "productName": "Non Book Product ",
          "supc": "SDL887500248",
          "sku": "Update Sub category :2014-06-19 10:56:34.277",
          "subOrderId": "44778377",
          "sellingPrice": 8252,
          "paymentMode": "COD",
          "orderDate": 1459501442000,
          "serialNumber": null,
          "siCode": "SI984130",
          "attributes": "",
          "serialNumberType": null,
          "sdInstant": false,
          "paymentDetail": null,
          "status": "Pending for Processing",
          "sellerUnrepliedCount": null,
          "issueReason": null,
          "caseStatus": null,
          "lastContentBody": null,
          "buyerFirstMessageTS": null,
          "buyerName": null,
          "caseId": null,
          "serverTime": null
        }
      ],
      "handoverId": null,
      "manifestedCode": null,
      "fpCode": "OC-DEL",
      "orderSla": null,
      "fastshipSla": null
    },
    {
      "packageReferenceCode": "SLP990631",
      "awbNumber": "103975677",
      "shippedOn": 1459873660000,
      "deliveredOn": null,
      "handoverDate": 1459873660000,
      "courierName": "XpressBees",
      "courierCode": "XPRESSBEES",
      "fulfillmentModeCode": "ONESHIP",
      "fulfillmentMode": "Oneship",
      "invoiceNumber": "",
      "stateFormRequired": false,
      "sdInstant": false,
      "orders": [
        {
          "productImageURL": "http://qan3.sdlcdn.com/imgs/a/a/0/107x125/Mahindra_The_New_Generation_Scorpio_SDL194819370_1_215b4-5d504.jpg",
          "productName": "Non Book Product ",
          "supc": "SDL887500248",
          "sku": "Update Sub category :2014-06-19 10:56:34.277",
          "subOrderId": "44948996",
          "sellingPrice": 1371,
          "paymentMode": "STD",
          "orderDate": 1459528684000,
          "serialNumber": null,
          "siCode": "SI1002613",
          "attributes": "",
          "serialNumberType": null,
          "sdInstant": false,
          "paymentDetail": null,
          "status": "Pending for Processing",
          "sellerUnrepliedCount": null,
          "issueReason": null,
          "caseStatus": null,
          "lastContentBody": null,
          "buyerFirstMessageTS": null,
          "buyerName": null,
          "caseId": null,
          "serverTime": null
        }
      ],
      "handoverId": null,
      "manifestedCode": null,
      "fpCode": "OC-DEL",
      "orderSla": null,
      "fastshipSla": null
    },
    {
      "packageReferenceCode": "SLP968483",
      "awbNumber": "103975677",
      "shippedOn": 1459841928000,
      "deliveredOn": null,
      "handoverDate": 1459841928000,
      "courierName": "XpressBees",
      "courierCode": "XPRESSBEES",
      "fulfillmentModeCode": "ONESHIP",
      "fulfillmentMode": "Oneship",
      "invoiceNumber": "",
      "stateFormRequired": false,
      "sdInstant": false,
      "orders": [
        {
          "productImageURL": "http://qan3.sdlcdn.com/imgs/a/a/0/107x125/Mahindra_The_New_Generation_Scorpio_SDL194819370_1_215b4-5d504.jpg",
          "productName": "Non Book Product ",
          "supc": "SDL887500248",
          "sku": "Update Sub category :2014-06-19 10:56:34.277",
          "subOrderId": "44753491",
          "sellingPrice": 8252,
          "paymentMode": "STD",
          "orderDate": 1459496328000,
          "serialNumber": null,
          "siCode": "SI980427",
          "attributes": "",
          "serialNumberType": null,
          "sdInstant": false,
          "paymentDetail": null,
          "status": "Pending for Processing",
          "sellerUnrepliedCount": null,
          "issueReason": null,
          "caseStatus": null,
          "lastContentBody": null,
          "buyerFirstMessageTS": null,
          "buyerName": null,
          "caseId": null,
          "serverTime": null
        }
      ],
      "handoverId": null,
      "manifestedCode": null,
      "fpCode": "OC-DEL",
      "orderSla": null,
      "fastshipSla": null
    },
    {
      "packageReferenceCode": "SLP988377",
      "awbNumber": "103975677",
      "shippedOn": 1459868442000,
      "deliveredOn": null,
      "handoverDate": 1459868442000,
      "courierName": "XpressBees",
      "courierCode": "XPRESSBEES",
      "fulfillmentModeCode": "ONESHIP",
      "fulfillmentMode": "Oneship",
      "invoiceNumber": "",
      "stateFormRequired": false,
      "sdInstant": false,
      "orders": [
        {
          "productImageURL": "http://qan3.sdlcdn.com/imgs/a/a/0/107x125/Mahindra_The_New_Generation_Scorpio_SDL194819370_1_215b4-5d504.jpg",
          "productName": "Non Book Product ",
          "supc": "SDL887500248",
          "sku": "Update Sub category :2014-06-19 10:56:34.277",
          "subOrderId": "44906658",
          "sellingPrice": 1371,
          "paymentMode": "STD",
          "orderDate": 1459522842000,
          "serialNumber": null,
          "siCode": "SI1000357",
          "attributes": "",
          "serialNumberType": null,
          "sdInstant": false,
          "paymentDetail": null,
          "status": "Pending for Processing",
          "sellerUnrepliedCount": null,
          "issueReason": null,
          "caseStatus": null,
          "lastContentBody": null,
          "buyerFirstMessageTS": null,
          "buyerName": null,
          "caseId": null,
          "serverTime": null
        }
      ],
      "handoverId": null,
      "manifestedCode": null,
      "fpCode": "OC-DEL",
      "orderSla": null,
      "fastshipSla": null
    },
    {
      "packageReferenceCode": "SLP974072",
      "awbNumber": "103975677",
      "shippedOn": 1459849079000,
      "deliveredOn": null,
      "handoverDate": 1459849079000,
      "courierName": "XpressBees",
      "courierCode": "XPRESSBEES",
      "fulfillmentModeCode": "ONESHIP",
      "fulfillmentMode": "Oneship",
      "invoiceNumber": "",
      "stateFormRequired": false,
      "sdInstant": false,
      "orders": [
        {
          "productImageURL": "http://qan3.sdlcdn.com/imgs/a/a/0/107x125/Mahindra_The_New_Generation_Scorpio_SDL194819370_1_215b4-5d504.jpg",
          "productName": "Non Book Product ",
          "supc": "SDL887500248",
          "sku": "Update Sub category :2014-06-19 10:56:34.277",
          "subOrderId": "44820735",
          "sellingPrice": 8252,
          "paymentMode": "STD",
          "orderDate": 1459503480000,
          "serialNumber": null,
          "siCode": "SI986000",
          "attributes": "",
          "serialNumberType": null,
          "sdInstant": false,
          "paymentDetail": null,
          "status": "Pending for Processing",
          "sellerUnrepliedCount": null,
          "issueReason": null,
          "caseStatus": null,
          "lastContentBody": null,
          "buyerFirstMessageTS": null,
          "buyerName": null,
          "caseId": null,
          "serverTime": null
        }
      ],
      "handoverId": null,
      "manifestedCode": null,
      "fpCode": "OC-DEL",
      "orderSla": null,
      "fastshipSla": null
    }
  ],
  "hasNext": true
}
